colorpaletteconverter.py
colorpaletteconverter-0.3.1.dist-info/LICENSE.txt
colorpaletteconverter-0.3.1.dist-info/METADATA
colorpaletteconverter-0.3.1.dist-info/WHEEL
colorpaletteconverter-0.3.1.dist-info/top_level.txt
colorpaletteconverter-0.3.1.dist-info/RECORD
