Metadata-Version: 2.1
Name: colorpaletteconverter
Version: 0.3.1
Summary: Make a MacOS Color palette from Python
Home-page: https://github.com/Rutger0000/colorpalette-converter
Author: Rutger Berns
Author-email: rutgerb0000@gmail.com
Classifier: Environment :: MacOS X
Classifier: Environment :: MacOS X :: Cocoa
Classifier: Programming Language :: Python :: 3
Classifier: Programming Language :: Python :: 3.7
Classifier: Programming Language :: Python :: 3.8
Classifier: License :: OSI Approved :: MIT License
Classifier: Operating System :: MacOS
Classifier: Topic :: Multimedia
License-File: LICENSE.txt
Requires-Dist: pyobjc-core ~=10.2
Requires-Dist: pyobjc-framework-Cocoa ~=10.2
Provides-Extra: dev
Requires-Dist: pytest >=5.2 ; extra == 'dev'
